LICENSE
README.md
setup.py
chamd/__init__.py
chamd/__main__.py
chamd/chat_reader.py
chamd/cleanCHILDESMD.py
chamd.egg-info/PKG-INFO
chamd.egg-info/SOURCES.txt
chamd.egg-info/dependency_links.txt
chamd.egg-info/entry_points.txt
chamd.egg-info/top_level.txt
chamd.egg-info/zip-safe
tests/test_chamd.py