Metadata-Version: 2.1
Name: chamd
Version: 0.5.11
Summary: Conversion and cleaning of CHILDES CHA files into PaQu Plaintext Metadata Format
Home-page: https://github.com/UUDigitalHumanitieslab/chamd
Author: Digital Humanities Lab, Utrecht University
Author-email: digitalhumanities@uu.nl
License: MIT
Requires-Python: >=3.5, <4
License-File: LICENSE
